Workbook

Sheet Techniques
A1: Technique ID | B1: Technique | C1: Description | D1: Tactic ID | E1: Tactic Name
A2: F1001 | B2: 3DS Bypass | C2: Fraud actors may exploit weaknesses in 3-Domain Secure authentication implementations to bypass additional security verification for card-not-present transactions. This may include deliberately providing incomplete cardholder information to cause authentication failures that result in transactions being processed without additional verification. Bypassing 3DS authentication allows fraud actors to conduct fraudulent transactions without completing the additional security challenges designed to prevent card-not-present fraud. | D2: {=IF(E2="","",_xlfn.LET( _xlpm.text,E2, _xlpm.split,_xlfn.TEXTSPLIT(_xlpm.text,", "), _xlpm.ids,_xlfn.MAP(_xlpm.split,_xlfn.LAMBDA(_xlpm.name,INDEX(Tactics!$A$2:$A$10,MATCH(TRIM(_xlpm.name),Tactics!$B$2:$B$10,0)))), _xlfn.TEXTJOIN(", ",TRUE,_xlpm.ids) ))} -> TA0005 | E2: Stealth
A3: T1453 | B3: Abuse Accessibility Features | C3: Fraud actors may abuse accessibility features on mobile devices to intercept and manipulate authentication processes. Malicious applications may request accessibility service permissions, enabling them to monitor screen content, intercept authentication prompts, and capture one-time passwords or other multi-factor authentication codes displayed on the device. This technique allows fraud actors to bypass security controls by gaining unauthorized access to sensitive information presented through legitimate authentication interfaces. | D3: {=IF(E3="","",_xlfn.LET( _xlpm.text,E3, _xlpm.split,_xlfn.TEXTSPLIT(_xlpm.text,", "), _xlpm.ids,_xlfn.MAP(_xlpm.split,_xlfn.LAMBDA(_xlpm.name,INDEX(Tactics!$A$2:$A$10,MATCH(TRIM(_xlpm.name),Tactics!$B$2:$B$10,0)))), _xlfn.TEXTJOIN(", ",TRUE,_xlpm.ids) ))} -> FA0001 | E3: Positioning
A4: F1002 | B4: Abuse of Public-Facing API | C4: Fraud actors may exploit publicly available APIs intended for legitimate customer or partner use to facilitate fraud operations. This may include account enumeration, credential stuffing attacks, data scraping, or automated financial transaction fraud. Fraud actors often leverage compromised credentials, botnets, or custom scripts to generate high volumes of API requests that mimic legitimate traffic patterns. | D4: {=IF(E4="","",_xlfn.LET( _xlpm.text,E4, _xlpm.split,_xlfn.TEXTSPLIT(_xlpm.text,", "), _xlpm.ids,_xlfn.MAP(_xlpm.split,_xlfn.LAMBDA(_xlpm.name,INDEX(Tactics!$A$2:$A$10,MATCH(TRIM(_xlpm.name),Tactics!$B$2:$B$10,0)))), _xlfn.TEXTJOIN(", ",TRUE,_xlpm.ids) ))} -> TA0001, TA0002, FA0001 | E4: Initial Access, Execution, Positioning
A5: F1002.001 | B5: Abuse of Public-Facing API: Mobile API Abuse | C5: Fraud actors may exploit mobile-specific APIs to conduct fraud operations. This may include using modified mobile applications, mobile device emulators, or custom scripts to generate fraudulent API calls that appear legitimate. Fraud actors target mobile APIs to bypass security controls designed for web-based access or to exploit mobile-specific vulnerabilities in authentication and authorization mechanisms. | D5: {=IF(E5="","",_xlfn.LET( _xlpm.text,E5, _xlpm.split,_xlfn.TEXTSPLIT(_xlpm.text,", "), _xlpm.ids,_xlfn.MAP(_xlpm.split,_xlfn.LAMBDA(_xlpm.name,INDEX(Tactics!$A$2:$A$10,MATCH(TRIM(_xlpm.name),Tactics!$B$2:$B$10,0)))), _xlfn.TEXTJOIN(", ",TRUE,_xlpm.ids) ))} -> TA0001, TA0002, FA0001 | E5: Initial Access, Execution, Positioning
A6: F1002.002 | B6: Abuse of Public-Facing API: Web API Abuse | C6: Fraud actors may abuse web-based APIs exposed through websites or web applications to automate fraud operations. This may include leveraging botnets, proxy networks, or headless browsers to mimic legitimate web traffic while conducting credential stuffing, transaction fraud, or data exfiltration. Fraud actors exploit web APIs to bypass rate limiting, CAPTCHA controls, or other security mechanisms designed to prevent automated abuse. | D6: {=IF(E6="","",_xlfn.LET( _xlpm.text,E6, _xlpm.split,_xlfn.TEXTSPLIT(_xlpm.text,", "), _xlpm.ids,_xlfn.MAP(_xlpm.split,_xlfn.LAMBDA(_xlpm.name,INDEX(Tactics!$A$2:$A$10,MATCH(TRIM(_xlpm.name),Tactics!$B$2:$B$10,0)))), _xlfn.TEXTJOIN(", ",TRUE,_xlpm.ids) ))} -> TA0001, TA0002, FA0001 | E6: Initial Access, Execution, Positioning
A7: F1003 | B7: Abuse SMS verification | C7: Fraud actors may abuse SMS verification and one-time-password (OTP) services to generate excessive messaging costs or facilitate toll‑fraud schemes, rather than to authenticate real users. In a common pattern, attackers script large numbers of account sign‑ups or login attempts that all trigger SMS verifications to premium‑rate or otherwise high‑tariff phone numbers they control, allowing them to collect a share of the inflated termination fees while the victim organization pays the messaging bill. Adversaries may also manipulate SMS routing by steering verification traffic through specific high‑cost international carriers or number ranges, disguising these as normal mobile destinations so that automated routing systems deliver the messages without suspicion. By driving sustained volumes of verification traffic into these expensive routes, attackers can rapidly increase the victim’s telecom spend and monetize the difference between actual delivery cost and what the organization expects to pay for legitimate verification usage. This technique focuses on cost and routing abuse of SMS verification itself, and is distinct from Multi-Factor Authenticaion Request Generation, which covers triggering MFA prompts or notifications to overwhelm or pressure vicitims into approving authenticaion attempts. | D7: {=IF(E7="","",_xlfn.LET( _xlpm.text,E7, _xlpm.split,_xlfn.TEXTSPLIT(_xlpm.text,", "), _xlpm.ids,_xlfn.MAP(_xlpm.split,_xlfn.LAMBDA(_xlpm.name,INDEX(Tactics!$A$2:$A$10,MATCH(TRIM(_xlpm.name),Tactics!$B$2:$B$10,0)))), _xlfn.TEXTJOIN(", ",TRUE,_xlpm.ids) ))} -> TA0002 | E7: Execution
A8: F1004 | B8: Access with Stolen Session Cookie | C8: Fraud actors may use stolen session cookies to gain unauthorized access to user accounts without requiring authentication credentials. Session cookies maintain user login state and may be obtained through phishing, malware, network interception, or data breaches. By replaying stolen session cookies, fraud actors can impersonate legitimate users and access accounts as long as the session remains valid. | D8: {=IF(E8="","",_xlfn.LET( _xlpm.text,E8, _xlpm.split,_xlfn.TEXTSPLIT(_xlpm.text,", "), _xlpm.ids,_xlfn.MAP(_xlpm.split,_xlfn.LAMBDA(_xlpm.name,INDEX(Tactics!$A$2:$A$10,MATCH(TRIM(_xlpm.name),Tactics!$B$2:$B$10,0)))), _xlfn.TEXTJOIN(", ",TRUE,_xlpm.ids) ))} -> TA0001 | E8: Initial Access
A9: T1531 | B9: Account Access Removal | C9: Fraud actors may remove or alter account access controls after gaining unauthorized access to lock out legitimate account owners. This may include changing login credentials, modifying account recovery information, or manipulating user roles and permissions within enterprise systems. By preventing the legitimate owner from regaining access, fraud actors maintain persistent control over compromised accounts. | D9: {=IF(E9="","",_xlfn.LET( _xlpm.text,E9, _xlpm.split,_xlfn.TEXTSPLIT(_xlpm.text,", "), _xlpm.ids,_xlfn.MAP(_xlpm.split,_xlfn.LAMBDA(_xlpm.name,INDEX(Tactics!$A$2:$A$10,MATCH(TRIM(_xlpm.name),Tactics!$B$2:$B$10,0)))), _xlfn.TEXTJOIN(", ",TRUE,_xlpm.ids) ))} -> FA0001 | E9: Positioning
A10: F1005 | B10: Account Manipulation | C10: Fraud actors may modify account settings to facilitate fraud operations or maintain persistent access. This may include altering payment methods, changing contact information, modifying notification preferences, adjusting security settings, linking accounts, or adding users. . Fraud actors typically gain initial access through stolen credentials or system vulnerabilities, then make unauthorized changes to account configurations to support subsequent fraud activities or prevent detection. | D10: {=IF(E10="","",_xlfn.LET( _xlpm.text,E10, _xlpm.split,_xlfn.TEXTSPLIT(_xlpm.text,", "), _xlpm.ids,_xlfn.MAP(_xlpm.split,_xlfn.LAMBDA(_xlpm.name,INDEX(Tactics!$A$2:$A$10,MATCH(TRIM(_xlpm.name),Tactics!$B$2:$B$10,0)))), _xlfn.TEXTJOIN(", ",TRUE,_xlpm.ids) ))} -> FA0001, TA0112 | E10: Positioning, Defense Impairment
A11: F1005.001 | B11: Account Manipulation: Account Linking | C11: Fraud actors may link compromised accounts to accounts under their control to establish persistent access that survives credential resets. In online and mobile banking environments, fraud actors may link victim bank accounts to secondary credentials or profiles without the victim's knowledge. This technique allows fraud actors to maintain account access even after the victim changes primary authentication credentials. | D11: {=IF(E11="","",_xlfn.LET( _xlpm.text,E11, _xlpm.split,_xlfn.TEXTSPLIT(_xlpm.text,", "), _xlpm.ids,_xlfn.MAP(_xlpm.split,_xlfn.LAMBDA(_xlpm.name,INDEX(Tactics!$A$2:$A$10,MATCH(TRIM(_xlpm.name),Tactics!$B$2:$B$10,0)))), _xlfn.TEXTJOIN(", ",TRUE,_xlpm.ids) ))} -> FA0001, TA0112 | E11: Positioning, Defense Impairment
A12: F1005.002 | B12: Account Manipulation: Add Authorized User | C12: Fraud actors may add themselves or accomplices as authorized users or secondary signers on compromised accounts. Authorized users typically have permission to perform transactions and access account features on behalf of the primary account holder. This technique provides fraud actors with legitimate-appearing access to accounts and may be used to position access for monetization or to establish persistent access that appears authorized. | D12: {=IF(E12="","",_xlfn.LET( _xlpm.text,E12, _xlpm.split,_xlfn.TEXTSPLIT(_xlpm.text,", "), _xlpm.ids,_xlfn.MAP(_xlpm.split,_xlfn.LAMBDA(_xlpm.name,INDEX(Tactics!$A$2:$A$10,MATCH(TRIM(_xlpm.name),Tactics!$B$2:$B$10,0)))), _xlfn.TEXTJOIN(", ",TRUE,_xlpm.ids) ))} -> FA0001, TA0112 | E12: Positioning, Defense Impairment
A13: F1005.003 | B13: Account Manipulation: Add Beneficiary | C13: Fraud actors may add themselves or accounts under their control as beneficiaries on compromised financial accounts. Beneficiary designations determine who receives account assets or benefits after the account holder's death or under other specified conditions. This technique allows fraud actors to potentially receive account assets in the future or to establish fraudulent claims to account benefits. | D13: {=IF(E13="","",_xlfn.LET( _xlpm.text,E13, _xlpm.split,_xlfn.TEXTSPLIT(_xlpm.text,", "), _xlpm.ids,_xlfn.MAP(_xlpm.split,_xlfn.LAMBDA(_xlpm.name,INDEX(Tactics!$A$2:$A$10,MATCH(TRIM(_xlpm.name),Tactics!$B$2:$B$10,0)))), _xlfn.TEXTJOIN(", ",TRUE,_xlpm.ids) ))} -> FA0001, TA0112 | E13: Positioning, Defense Impairment
... A124: F1048 | B124: Use Virtual Cards | C124: Fraud actors use virtual cards to facilitate online fraud because they provide flexibility, anonymity, and rapid issuance for card‑not‑present transactions. Virtual cards are often obtained with weaker identity verification or sourced from compromised accounts, making them attractive instruments for testing stolen card data, funding mule accounts, or executing rapid series of purchases and refunds. Their disposability allows fraud actors to run multiple transactions, dispute or reverse charges, and then discard the card, reducing the risk that a single compromised instrument links together the broader scheme. Virtual cards are frequently employed in promotion abuse, synthetic identity fraud, and account takeover scenarios, for example, to cash out loyalty points, rotate through trial or subscription offers, or route payments through intermediary wallets and marketplaces. They can also be used to create complex transaction chains across merchants and jurisdictions, complicating efforts to tie specific fraudulent purchases back to the originating compromised identity or account. This flexibility makes virtual cards a convenient tool for scaling and obscuring a wide range of digital fraud schemes, even when they are not explicitly part of a formal money‑laundering process. | D124: {=IF(E124="","",_xlfn.LET( _xlpm.text,E124, _xlpm.split,_xlfn.TEXTSPLIT(_xlpm.text,", "), _xlpm.ids,_xlfn.MAP(_xlpm.split,_xlfn.LAMBDA(_xlpm.name,INDEX(Tactics!$A$2:$A$10,MATCH(TRIM(_xlpm.name),Tactics!$B$2:$B$10,0)))), _xlfn.TEXTJOIN(", ",TRUE,_xlpm.ids) ))} -> TA0005 | E124: Stealth

Sheet Tactics
A1: Tactic ID | B1: Tactic Name | C1: Tactic Description
A2: TA0043 | B2: Reconnaissance | C2: The fraud actor's actions to gather information they can use to plan future operations, including both cyber intrusions and attempted fraud. Reconnaissance consists of techniques that involve fraud actors actively or passively gathering information that can be used to support targeting. Such information may include details of the victim organization, infrastructure, or staff/personnel. This information can be leveraged by the fraud actor to aid in other phases of the fraud lifecycle, such as using gathered information to plan and execute Initial Access, to scope and prioritize post-compromise objectives, or to drive and lead further Reconnaissance efforts.
A3: TA0042 | B3: Resource Development | C3: The fraud actor's actions to establish resources they can use to support both cyber and fraud activities. Resource Development consists of techniques that involve fraud actors creating, purchasing, or compromising/stealing resources that can be used to support targeting. Such resources include infrastructure, accounts, or capabilities. These resources can be leveraged by the fraud actor to aid in other phases of the fraud lifecycle, such as using purchased domains to support Execution, email accounts for phishing as a part of Initial Access, or spoofing to help with Stealth.
A4: TA0001 | B4: Initial Access | C4: The fraud actor's actions to gain a foothold in a selected environment. Initial Access consists of techniques that use various entry vectors to gain their initial foothold within a selected environment. Techniques used to gain a foothold include targeted spearphishing and exploiting weaknesses in browsers. Footholds gained through initial access may allow for continued access, like compromise accounts and use of external remote services, or may be limited-use due to changing passwords.
A5: TA0005 | B5: Stealth | C5: The fraud actor is trying to hide and conceal fraudulent activity by appearing as normal user or business behavior. Stealth consists of techniques that reduce the likelihood of detection by blending in with legitimate activity or minimizing observable indicators of fraud. These techniques are characterized by concealment behaviors such as obfuscation, impersonation, traffic shaping, or mimicking normal customer operations, without directly modifying security controls or monitoring systems. The goal is to remain indistinguishable from benign activity while leaving defensive systems operational and intact.
A6: TA0112 | B6: Defense Impairment | C6: The fraud actor is trying to break or undermine security mechanisms, fraud controls, or customer safeguards, so defenders or victims cannot respond to fraudulent activity. Defense Impairment consists of techniques that degrade, disable, evade, or undermine the effectiveness and trustworthiness of security controls, fraud prevention systems, and customer-facing security features. This is characterized by direct interference with defensive technologies, operational processes, or user security controls. This may include disabling account alerts, suppressing notifications, modifying contact information, or bypassing authentication safeguards. The goal is to reduce the ability of organizations and victims to identify, prevent, or respond to fraud activity.
A7: FA0001 | B7: Positioning | C7: The fraud actor's actions in a selected environment, after initial access, to collect or manipulate data or otherwise prepare for execution. Positioning consists of techniques that involve fraud actors gathering sensitive information, altering account configurations, manipulating transaction parameters, or establishing conditions necessary for successful fraud operations. These preparatory activities enable fraud actors to maximize the value extracted during fraud execution or establish persistent access for future operations.
A8: TA0002 | B8: Execution | C8: The fraud actor's actions to run malicious code or initiate fraudulent transactions that will convert stolen data to money. Execution consists of techniques that result in fraud actor‑controlled code or actions running on a local, remote, or transaction‑processing system. Techniques that run malicious code or automate actions are often paired with other tactics to achieve broader goals, such as exploring a network, manipulating applications, initiating unauthorized payments, or altering transaction data to support fraud. For example, a fraud actor might use a remote access tool to run a PowerShell script that performs Remote System Discovery and then launch scripts or bots that submit fraudulent transfers, modify payment instructions, or replay payment messages through compromised banking or merchant platforms.
A9: FA0002 | B9: Monetization | C9: The fraud actor's actions to convert assets, often stolen, into usable funds or value in their possession. Fraud actors may convert fraudulently obtained funds or assets into a form they can utilize or transfer to their possession. Monetization consists of techniques that involve fraud actors liquidating stolen digital assets, transferring funds from compromised accounts, converting fraud proceeds into difficult-to-trace monetary instruments, or manipulating markets. These techniques represent the final stages of fraud operations where fraud actors secure their gains and attempt to obscure the transaction trail.
